opensesame/__init__.py
opensesame/__main__.py
opensesame/clipboard.py
opensesame/error.py
opensesame/helpers.py
opensesame/letters.py
opensesame/list.txt
opensesame/main_click.py
opensesame/password.py
opensesame/words.py
pyopensesame-1.0.1.dist-info/METADATA
pyopensesame-1.0.1.dist-info/WHEEL
pyopensesame-1.0.1.dist-info/entry_points.txt
pyopensesame-1.0.1.dist-info/top_level.txt
pyopensesame-1.0.1.dist-info/RECORD
