Metadata-Version: 2.1
Name: pyopensesame
Version: 1.0.1
Summary: Advanced password generator and hasher
Author: Adam Jenca
Author-email: jenca.a@gjh.sk
Project-URL: GitHub, https://github.com/jenca-adam/opensesame/
Classifier: Development Status :: 4 - Beta
Classifier: Intended Audience :: Developers
Classifier: Operating System :: OS Independent
Classifier: License :: OSI Approved :: GNU General Public License v3 (GPLv3)
Requires-Dist: click
Requires-Dist: click-default-group
